awsswapper/__init__.py
awsswapper-0.2.0.dist-info/WHEEL
awsswapper-0.2.0.dist-info/entry_points.txt
awsswapper-0.2.0.dist-info/METADATA
awsswapper-0.2.0.dist-info/RECORD
