Metadata-Version: 2.1
Name: awsswapper
Version: 0.2.0
Summary: 
Author: Willem Thiart
Author-email: himself@willemthiart.com
Requires-Python: >=3.7,<4.0
Classifier: Programming Language :: Python :: 3
Classifier: Programming Language :: Python :: 3.7
Classifier: Programming Language :: Python :: 3.8
Classifier: Programming Language :: Python :: 3.9
Classifier: Programming Language :: Python :: 3.10
Classifier: Programming Language :: Python :: 3.11
Requires-Dist: boto3 (>=1.17.75,<2.0.0)
Requires-Dist: cliar (>=1.3.4,<2.0.0)
